openmaptiles/__init__.py
openmaptiles/diagram.py
openmaptiles/docs.py
openmaptiles/imposm.py
openmaptiles/language.py
openmaptiles/sql.py
openmaptiles/tileset.py
openmaptiles/tmsource.py
openmaptiles_tools-0.9.2.data/scripts/generate-diagram-pngs
openmaptiles_tools-0.9.2.data/scripts/generate-doc
openmaptiles_tools-0.9.2.data/scripts/generate-etlgraph
openmaptiles_tools-0.9.2.data/scripts/generate-imposm3
openmaptiles_tools-0.9.2.data/scripts/generate-mapping-graph
openmaptiles_tools-0.9.2.data/scripts/generate-metadata
openmaptiles_tools-0.9.2.data/scripts/generate-sql
openmaptiles_tools-0.9.2.data/scripts/generate-sqlquery
openmaptiles_tools-0.9.2.data/scripts/generate-tm2source
openmaptiles_tools-0.9.2.dist-info/METADATA
openmaptiles_tools-0.9.2.dist-info/RECORD
openmaptiles_tools-0.9.2.dist-info/WHEEL
openmaptiles_tools-0.9.2.dist-info/top_level.txt
