Metadata-Version: 2.1
Name: openmaptiles-tools
Version: 0.9.2
Summary: The OpenMapTiles tools for generating TM2Source projects, imposm3 mappings and SQL instructions from OpenMapTiles layers. We encourage other people to use this for their vector tile projects as well since this approach works well for us.
Home-page: https://github.com/openmaptiles/openmaptiles-tools
License: MIT
Platform: UNKNOWN
Requires-Dist: docopt
Requires-Dist: pyyaml
Requires-Dist: graphviz
